dadjokeAPI/__init__.py
dadjokeAPI/dadjokeAPI.py
dadjokeAPI/exceptions.py
dadjokeAPI-1.0.4.dist-info/METADATA
dadjokeAPI-1.0.4.dist-info/WHEEL
dadjokeAPI-1.0.4.dist-info/top_level.txt
dadjokeAPI-1.0.4.dist-info/RECORD
