Metadata-Version: 2.1
Name: dadjokeAPI
Version: 1.0.4
Summary: A simple API wrapper for your dad joke needs.
Home-page: https://github.com/7ez/dadjokeAPI
Author: Aochi
Author-email: aochi@fuquila.net
License: UNKNOWN
Platform: UNKNOWN
Classifier: Programming Language :: Python :: 3
Classifier: License :: OSI Approved :: MIT License
Classifier: Operating System :: OS Independent
Requires-Python: >=3.7
Requires-Dist: aiohttp
Requires-Dist: requests
